pyopendrive/__init__.py
pyopendrive/pyopendrive.py
pyopendrive-0.0.1.1.dist-info/AUTHORS.rst
pyopendrive-0.0.1.1.dist-info/LICENSE
pyopendrive-0.0.1.1.dist-info/METADATA
pyopendrive-0.0.1.1.dist-info/WHEEL
pyopendrive-0.0.1.1.dist-info/top_level.txt
pyopendrive-0.0.1.1.dist-info/RECORD
